clouddrive/__init__.py
clouddrive/__main__.py
clouddrive/client.py
clouddrive/gen_client.py
clouddrive/pb2.py
clouddrive/cmd/__init__.py
clouddrive/cmd/download.py
clouddrive/cmd/init.py
clouddrive/cmd/iterdir.py
clouddrive/cmd/rename.py
clouddrive/cmd/upload.py
clouddrive/cmd/fuse/__init__.py
clouddrive/cmd/fuse/__main__.py
clouddrive/cmd/fuse/util/__fuse_monkey_patch.py
clouddrive/cmd/fuse/util/__init__.py
clouddrive/cmd/fuse/util/fuser.py
clouddrive/cmd/fuse/util/log.py
clouddrive/cmd/fuse/util/predicate.py
clouddrive/cmd/fuse/util/strm.py
clouddrive/proto/CloudDrive_grpc.py
clouddrive/proto/CloudDrive_pb2.py
clouddrive/proto/CloudDrive_pb2_grpc.py
python_clouddrive2-2.0.8.1.2.dist-info/METADATA
python_clouddrive2-2.0.8.1.2.dist-info/WHEEL
python_clouddrive2-2.0.8.1.2.dist-info/entry_points.txt
python_clouddrive2-2.0.8.1.2.dist-info/licenses/LICENSE
python_clouddrive2-2.0.8.1.2.dist-info/RECORD
