Metadata-Version: 2.4
Name: python-clouddrive2
Version: 2.0.8.1.2
Summary: CloudDrive2 gRPC 客户端库，提供简洁易用的 Python API 来操作 CloudDrive2 服务
Project-URL: Homepage, https://github.com/iLay1678/python-clouddrive2
Project-URL: Repository, https://github.com/iLay1678/python-clouddrive2
Author-email: ChenyangGao <wosiwujm@gmail.com>, iLay1678 <ifwangs400@gmail.com>
License: MIT
License-File: LICENSE
Keywords: client,clouddrive
Classifier: Development Status :: 4 - Beta
Classifier: Intended Audience :: Developers
Classifier: License :: OSI Approved :: MIT License
Classifier: Operating System :: OS Independent
Classifier: Programming Language :: Python
Classifier: Programming Language :: Python :: 3
Classifier: Programming Language :: Python :: 3 :: Only
Classifier: Programming Language :: Python :: 3.11
Classifier: Topic :: Software Development
Classifier: Topic :: Software Development :: Libraries
Classifier: Topic :: Software Development :: Libraries :: Python Modules
Requires-Python: >=3.11
Requires-Dist: glob-pattern
Requires-Dist: grpcio
Requires-Dist: grpcio-tools
Requires-Dist: grpclib
Requires-Dist: grpclib[protobuf]
Requires-Dist: http-response
Requires-Dist: path-ignore-pattern
Requires-Dist: protobuf
Requires-Dist: python-argtools
Requires-Dist: python-dateutil
Requires-Dist: python-download>=0.0.3
Requires-Dist: python-filewrap>=0.1.1
Requires-Dist: python-http-request>=0.0.6
Requires-Dist: python-httpfile>=0.0.2
Requires-Dist: python-urlopen
Requires-Dist: yarl
